{
    "pools": [
        {
            "rolls": 1,
            "entries": [
                {
                    "type": "minecraft:item",
                    "weight": 1,
                    "functions": [
                        {
                            "function": "minecraft:set_nbt",
                            "tag": "{imm:{id:\"imm:vial_of_ichor\"},CustomModelData:402000}"
                        },
                        {
                            "function": "minecraft:set_name",
                            "name": {
                                "translate": "item.imm.vial_of_ichor",
                                "color": "aqua",
                                "italic": false
                            }
                        },
                        {
                            "function": "minecraft:set_lore",
                            "lore": [
                                {
                                    "translate": "pack.imm.tooltip",
                                    "color": "white",
                                    "italic": false,
                                    "font": "imm:tooltip",
                                    "with": [
                                        {
                                            "translate": "pack.imm",
                                            "color": "#9d1e2d",
                                            "italic": true,
                                            "font": "minecraft:default"
                                        }
                                    ]
                                },
                                "",
                                {
                                    "translate": "item.imm.vial_of_ichor.desc1",
                                    "color": "gray",
                                    "italic": false
                                },
                                [
                                    " ",
                                    {
                                        "translate": "item.imm.vial_of_ichor.desc2",
                                        "italic": false,
                                        "color": "blue"
                                    }
                                ],
                                [
                                    " ",
                                    {
                                        "translate": "item.imm.vial_of_ichor.desc3",
                                        "italic": false,
                                        "color": "blue"
                                    }
                                ]
                            ]
                        }
                    ],
                    "name": "minecraft:honey_bottle"
                }
            ]
        }
    ],
    "random_sequence": "imm:item/ectoplasm"
}